kipoi_interpret/__init__.py
kipoi_interpret/cli.py
kipoi_interpret/utils.py
kipoi_interpret/importance_scores/__init__.py
kipoi_interpret/importance_scores/base.py
kipoi_interpret/importance_scores/cli.py
kipoi_interpret/importance_scores/gradient.py
kipoi_interpret/importance_scores/ism.py
kipoi_interpret/importance_scores/ism_scores.py
kipoi_interpret/importance_scores/referencebased.py
kipoi_interpret-0.1.2.dist-info/LICENSE
kipoi_interpret-0.1.2.dist-info/METADATA
kipoi_interpret-0.1.2.dist-info/WHEEL
kipoi_interpret-0.1.2.dist-info/top_level.txt
kipoi_interpret-0.1.2.dist-info/RECORD
